EdiHeadyTrack/__init__.py
EdiHeadyTrack/camera.py
EdiHeadyTrack/filter.py
EdiHeadyTrack/imu.py
EdiHeadyTrack/plot.py
EdiHeadyTrack/posedetector.py
EdiHeadyTrack/sensordata.py
EdiHeadyTrack/video.py
EdiHeadyTrack/TDDFA_v2/TDDFA copy.py
EdiHeadyTrack/TDDFA_v2/TDDFA.py
EdiHeadyTrack/TDDFA_v2/TDDFA_ONNX.py
EdiHeadyTrack/TDDFA_v2/__init__.py
EdiHeadyTrack/TDDFA_v2/demo.py
EdiHeadyTrack/TDDFA_v2/demo_video.py
EdiHeadyTrack/TDDFA_v2/demo_video_smooth.py
EdiHeadyTrack/TDDFA_v2/demo_webcam_smooth.py
EdiHeadyTrack/TDDFA_v2/gradiodemo.py
EdiHeadyTrack/TDDFA_v2/latency.py
EdiHeadyTrack/TDDFA_v2/speed_cpu.py
EdiHeadyTrack/TDDFA_v2/FaceBoxes/FaceBoxes.py
EdiHeadyTrack/TDDFA_v2/FaceBoxes/FaceBoxes_ONNX.py
EdiHeadyTrack/TDDFA_v2/FaceBoxes/__init__.py
EdiHeadyTrack/TDDFA_v2/FaceBoxes/onnx.py
EdiHeadyTrack/TDDFA_v2/FaceBoxes/models/__init__.py
EdiHeadyTrack/TDDFA_v2/FaceBoxes/models/faceboxes.py
EdiHeadyTrack/TDDFA_v2/FaceBoxes/utils/__init__.py
EdiHeadyTrack/TDDFA_v2/FaceBoxes/utils/box_utils.py
EdiHeadyTrack/TDDFA_v2/FaceBoxes/utils/build.py
EdiHeadyTrack/TDDFA_v2/FaceBoxes/utils/config.py
EdiHeadyTrack/TDDFA_v2/FaceBoxes/utils/functions.py
EdiHeadyTrack/TDDFA_v2/FaceBoxes/utils/nms_wrapper.py
EdiHeadyTrack/TDDFA_v2/FaceBoxes/utils/prior_box.py
EdiHeadyTrack/TDDFA_v2/FaceBoxes/utils/timer.py
EdiHeadyTrack/TDDFA_v2/FaceBoxes/utils/nms/__init__.py
EdiHeadyTrack/TDDFA_v2/FaceBoxes/utils/nms/py_cpu_nms.py
EdiHeadyTrack/TDDFA_v2/FaceBoxes/weights/FaceBoxesProd.pth
EdiHeadyTrack/TDDFA_v2/Sim3DR/Sim3DR.py
EdiHeadyTrack/TDDFA_v2/Sim3DR/__init__.py
EdiHeadyTrack/TDDFA_v2/Sim3DR/_init_paths.py
EdiHeadyTrack/TDDFA_v2/Sim3DR/lighting.py
EdiHeadyTrack/TDDFA_v2/Sim3DR/setup.py
EdiHeadyTrack/TDDFA_v2/bfm/__init__.py
EdiHeadyTrack/TDDFA_v2/bfm/bfm.py
EdiHeadyTrack/TDDFA_v2/bfm/bfm_onnx.py
EdiHeadyTrack/TDDFA_v2/bfm copy/__init__.py
EdiHeadyTrack/TDDFA_v2/bfm copy/bfm.py
EdiHeadyTrack/TDDFA_v2/bfm copy/bfm_onnx.py
EdiHeadyTrack/TDDFA_v2/configs/.gitignore
EdiHeadyTrack/TDDFA_v2/configs/BFM_UV.mat
EdiHeadyTrack-0.2.2.dist-info/LICENSE
EdiHeadyTrack-0.2.2.dist-info/METADATA
EdiHeadyTrack-0.2.2.dist-info/WHEEL
EdiHeadyTrack-0.2.2.dist-info/top_level.txt
EdiHeadyTrack-0.2.2.dist-info/RECORD
