Metadata-Version: 2.1
Name: EdiHeadyTrack
Version: 0.2.2
Summary: Automatic, markerless measurement of head kinematics using from video
Home-page: https://github.com/isDynamics/EdiHeadyTrack
Author: Thomas Aston
Author-email: thomas.aston@ed.ac.uk
Classifier: Programming Language :: Python :: 3
Classifier: License :: OSI Approved :: Apache Software License
Classifier: Operating System :: OS Independent
Requires-Python: >=3.9
License-File: LICENSE
Requires-Dist: matplotlib
Requires-Dist: mediapipe
Requires-Dist: mock
Requires-Dist: numpy <1.24
Requires-Dist: pandas
Requires-Dist: scipy
Requires-Dist: setuptools
Requires-Dist: sphinx-rtd-theme
Requires-Dist: sphinx-mdinclude
Requires-Dist: nbsphinx
Requires-Dist: tqdm
Requires-Dist: torch
Requires-Dist: torchvision
Requires-Dist: opencv-python
Requires-Dist: imageio
Requires-Dist: imageio-ffmpeg
Requires-Dist: pyyaml
Requires-Dist: argparse
Requires-Dist: cython
Requires-Dist: scikit-image
Requires-Dist: onnxruntime
Requires-Dist: gradio
Requires-Dist: onnx
